odoo9_addon_account_move_line_purchase_info-9.0.1.0.0-py2.7-nspkg.pth
odoo9_addon_account_move_line_purchase_info-9.0.1.0.0.dist-info/top_level.txt
odoo9_addon_account_move_line_purchase_info-9.0.1.0.0.dist-info/WHEEL
odoo9_addon_account_move_line_purchase_info-9.0.1.0.0.dist-info/RECORD
odoo9_addon_account_move_line_purchase_info-9.0.1.0.0.dist-info/metadata.json
odoo9_addon_account_move_line_purchase_info-9.0.1.0.0.dist-info/DESCRIPTION.rst
odoo9_addon_account_move_line_purchase_info-9.0.1.0.0.dist-info/METADATA
odoo9_addon_account_move_line_purchase_info-9.0.1.0.0.dist-info/namespace_packages.txt
odoo_addons/account_move_line_purchase_info/__openerp__.py
odoo_addons/account_move_line_purchase_info/__init__.py
odoo_addons/account_move_line_purchase_info/README.rst
odoo_addons/account_move_line_purchase_info/security/account_security.xml
odoo_addons/account_move_line_purchase_info/models/stock.py
odoo_addons/account_move_line_purchase_info/models/account_invoice.py
odoo_addons/account_move_line_purchase_info/models/__init__.py
odoo_addons/account_move_line_purchase_info/models/account_move.py
odoo_addons/account_move_line_purchase_info/views/account_move_view.xml
odoo_addons/account_move_line_purchase_info/tests/__init__.py
odoo_addons/account_move_line_purchase_info/tests/test_account_move_line_purchase_info.py
odoo_addons/account_move_line_purchase_info/static/description/icon.png
